{"id":"0eNRxI4AFfdBX7tjk9dQY","title":"Pursuade","vault":{"fsPath":"repos/dendron-aws-vault","remote":{"type":"git","url":"https://github.com/cczhong11/my_note.git"},"name":"my_note"},"type":"note","desc":"","links":[],"anchors":{"现代科技的影响":{"type":"header","value":"现代科技的影响","line":12,"column":0},"媒体":{"type":"header","value":"媒体","line":20,"column":0},"广告":{"type":"header","value":"广告","line":28,"column":0},"说服":{"type":"header","value":"说服","line":34,"column":0},"沟通者的可信度":{"type":"header","value":"沟通者的可信度","line":44,"column":0},"沟通的性质":{"type":"header","value":"沟通的性质","line":54,"column":0},"接受者的特征":{"type":"header","value":"接受者的特征","line":77,"column":0},"说服的抗拒":{"type":"header","value":"说服的抗拒","line":88,"column":0}},"fname":"life.social.pursuade","updated":1629871361279,"created":1629867081566,"parent":"efxujPMmo91nKhmMDwmxy","children":[],"data":{},"contentHash":"2623a6fd53a4818d61956666f272a58e","custom":{}}
