{"id":"92f554c1-e947-4ee5-beab-e3c30ea1b5dd","title":"Consistency","vault":{"fsPath":"repos/dendron-aws-vault","remote":{"type":"git","url":"https://github.com/cczhong11/my_note.git"},"name":"my_note"},"type":"note","desc":"","links":[],"anchors":{"weak-consistency":{"type":"header","value":"weak-consistency","line":8,"column":0},"eventual-consistency":{"type":"header","value":"eventual-consistency","line":14,"column":0},"strong-consistency":{"type":"header","value":"strong-consistency","line":20,"column":0}},"fname":"development.database.concurrency.consistency","updated":1621009126969,"created":1621009111527,"parent":"c10c6c14-9f83-4681-8aef-74c7a20432b1","children":[],"data":{},"custom":{},"contentHash":"e4c000bf6426ac04f9872d78b07b1f78"}
