{"id":"dk7kr7xzrhq1wehrr3qhzoa","title":"Photobackup","desc":"","updated":1728458569285,"created":1694929185821,"custom":{},"fname":"life.automation.photobackup","type":"note","vault":{"fsPath":"repos/dendron-aws-vault","remote":{"type":"git","url":"https://github.com/cczhong11/my_note.git"},"name":"my_note"},"contentHash":"cfa5c7cc747698a9bdedec8be30b58ef","links":[],"anchors":{"photobackup":{"type":"header","text":"Photobackup","value":"photobackup","line":8,"column":0,"depth":1},"备份核心硬盘":{"type":"header","text":"备份核心硬盘","value":"备份核心硬盘","line":10,"column":0,"depth":2},"数据库":{"type":"header","text":"数据库","value":"数据库","line":14,"column":0,"depth":2},"程序":{"type":"header","text":"程序","value":"程序","line":19,"column":0,"depth":2},"手机照片":{"type":"header","text":"手机照片","value":"手机照片","line":26,"column":0,"depth":2},"清理":{"type":"header","text":"清理","value":"清理","line":31,"column":0,"depth":3}},"children":[],"parent":"bjj9gxh6yu1vdal4w8sttth","data":{}}
