{"id":"dQ7LzamBvvzyPTelGfLTQ","title":"Composition","vault":{"fsPath":"repos/dendron-aws-vault","remote":{"type":"git","url":"https://github.com/cczhong11/my_note.git"},"name":"my_note"},"type":"note","desc":"","links":[],"anchors":{"三分法":{"type":"header","value":"三分法","line":22,"column":0},"居中":{"type":"header","value":"居中","line":28,"column":0},"对称":{"type":"header","value":"对称","line":33,"column":0},"镜面对称":{"type":"header","value":"镜面对称","line":37,"column":0},"元素对称":{"type":"header","value":"元素对称","line":43,"column":0},"黄金螺旋":{"type":"header","value":"黄金螺旋","line":51,"column":0},"引导线构图":{"type":"header","value":"引导线构图","line":56,"column":0},"前景":{"type":"header","value":"前景","line":69,"column":0},"寻找画框":{"type":"header","value":"寻找画框","line":81,"column":0},"质感构图":{"type":"header","value":"质感构图","line":85,"column":0},"重复构图":{"type":"header","value":"重复构图","line":89,"column":0},"拍人":{"type":"header","value":"拍人","line":93,"column":0}},"fname":"life.photo.composition","updated":1631255483628,"created":1629871421592,"parent":"2b3acd33-5cae-41eb-9647-f69ca0fd04ab","children":[],"data":{},"contentHash":"2a54a9b1b7d6229573e576e8fe43375b","custom":{}}
